esmecata/__init__.py
esmecata/__main__.py
esmecata/__main_create_database__.py
esmecata/__main_gseapy__.py
esmecata/__main_report__.py
esmecata/utils.py
esmecata/core/annotation.py
esmecata/core/clustering.py
esmecata/core/eggnog.py
esmecata/core/precomputed.py
esmecata/core/proteomes.py
esmecata/core/workflow.py
esmecata/gseapy/gseapy_orsum.py
esmecata/report/ec_sunburst_per_model.py
esmecata/report/esmecata2taxontology.py
esmecata/report/esmecata_compression.py
esmecata/report/panel_report_creation.py
esmecata/report/report_creation.py
esmecata/report/stats_workflow_figures.py
esmecata/report/workflow_create_report.py
esmecata-0.6.9.dist-info/licenses/LICENSE
esmecata-0.6.9.dist-info/METADATA
esmecata-0.6.9.dist-info/WHEEL
esmecata-0.6.9.dist-info/entry_points.txt
esmecata-0.6.9.dist-info/top_level.txt
esmecata-0.6.9.dist-info/RECORD
