Metadata-Version: 2.4
Name: esmecata
Version: 0.6.9
Summary: EsMeCaTa: Estimating Metabolic Capabilties from Taxonomy
Author-email: AuReMe <gem-aureme@inria.fr>
License: GPL-3.0-or-later
Project-URL: Homepage, https://github.com/AuReMe/esmecata
Project-URL: Changelog, https://github.com/AuReMe/esmecata/blob/main/CHANGELOG.md
License-File: LICENSE
Requires-Dist: biopython
Requires-Dist: bioservices
Requires-Dist: ete4
Requires-Dist: matplotlib
Requires-Dist: pandas
Requires-Dist: requests
Requires-Dist: seaborn
Requires-Dist: SPARQLWrapper
Requires-Dist: numpy
Requires-Dist: scipy
Provides-Extra: analysis
Requires-Dist: arakawa; extra == "analysis"
Requires-Dist: plotly; extra == "analysis"
Requires-Dist: kaleido; extra == "analysis"
Requires-Dist: ontosunburst; extra == "analysis"
Provides-Extra: gseapy
Requires-Dist: bioservices; extra == "gseapy"
Requires-Dist: gseapy; extra == "gseapy"
Requires-Dist: orsum; extra == "gseapy"
Requires-Dist: pronto; extra == "gseapy"
Provides-Extra: test
Requires-Dist: pytest; extra == "test"
Requires-Dist: pytest-mock; extra == "test"
Dynamic: license-file
